supamodel/__init__.py
supamodel/_abc.py
supamodel/_client.py
supamodel/_core.py
supamodel/_logging.py
supamodel/_types.py
supamodel/config.py
supamodel/enums.py
supamodel/errors.py
supamodel/exceptions.py
supamodel/supa.py
supamodel/supa_builder.py
supamodel/utils.py
supamodel/abstract/__init__.py
supamodel/abstract/core.py
supamodel/abstract/data.py
supamodel/abstract/dataset.py
supamodel/abstract/query_params.py
supamodel/abstract/repository.py
supamodel/trading/__init__.py
supamodel/trading/assets.py
supamodel/trading/clock.py
supamodel/trading/exchange.py
supamodel/trading/market_data.py
supamodel/trading/order_management.py
supamodel/trading/portfolio.py
supamodel/trading/tokens.py
supamodel-0.6.6.dist-info/METADATA
supamodel-0.6.6.dist-info/WHEEL
supamodel-0.6.6.dist-info/RECORD
