Metadata-Version: 2.3
Name: supamodel
Version: 0.6.6
Summary: Pydantic Models for Trading Algos and Supabase
Author-email: Kevin Hill <kivo360@gmail.com>
Requires-Python: <=3.13,>=3.9
Requires-Dist: diskcache<6.0.0,>=5.6.3
Requires-Dist: email-validator>=2.2.0
Requires-Dist: inflector<4.0.0,>=3.1.1
Requires-Dist: lazy-object-proxy>=1.10.0
Requires-Dist: loguru<1.0.0,>=0.5.0
Requires-Dist: numpy<2.0.0,>=1.26.4
Requires-Dist: orjson<4.0.0,>=3.10.0
Requires-Dist: pandas<3.0.0,>=2.2.1
Requires-Dist: pendulum<4.0.0,>=2.0.0
Requires-Dist: pydantic-settings<=3.0.0,>=2.0.0
Requires-Dist: pydantic<3.0.0,>=2.5.0
Requires-Dist: rich<14.0.0,>=13.7.1
Requires-Dist: scipy<2.0.0,>=1.13.0
Requires-Dist: solana<0.34.0,>=0.33.0
Requires-Dist: solders<0.22.0,>=0.21.0
Requires-Dist: supabase<3.0.0,>=2.5.0
Requires-Dist: typer<0.13.0,>=0.12.3
